fresh_deps/__init__.py
fresh_deps/__main__.py
fresh_deps/_dependency_updater.py
fresh_deps/_gitlab_api.py
fresh_deps/_service_api.py
fresh_deps/_update_dependencies.py
fresh_deps/py.typed
freshdeps-1.0.3.dist-info/METADATA
freshdeps-1.0.3.dist-info/WHEEL
freshdeps-1.0.3.dist-info/entry_points.txt
freshdeps-1.0.3.dist-info/top_level.txt
freshdeps-1.0.3.dist-info/RECORD
