Metadata-Version: 2.1
Name: freshdeps
Version: 1.0.3
Summary: Keep your Python dependencies fresh
Home-page: https://github.com/Kater913/freshdeps
Author: Kate
Author-email: kater913@yandex.ru
Requires-Python: >=3.8
Requires-Dist: pip-tools ==6.9.0
Requires-Dist: plumbum ==1.8.0
Requires-Dist: python-gitlab ==3.10.0
